selectaudio/__init__.py
selectaudio/__main__.py
selectaudio-0.1.3.dist-info/COPYING
selectaudio-0.1.3.dist-info/METADATA
selectaudio-0.1.3.dist-info/WHEEL
selectaudio-0.1.3.dist-info/entry_points.txt
selectaudio-0.1.3.dist-info/top_level.txt
selectaudio-0.1.3.dist-info/RECORD
